{"frameRate":24,"name":"huodejiemian","version":"5.5","compatibleVersion":"5.5","armature":[{"type":"Armature","frameRate":24,"name":"huodejiemian","aabb":{"x":-299,"y":-242,"width":598,"height":413},"bone":[{"name":"root"},{"length":273,"name":"caidai","parent":"root","transform":{"x":-1.05,"skX":179.7798,"skY":179.7798}},{"length":270,"name":"saoguang","parent":"root","transform":{"y":2.1,"skX":-90,"skY":-90}},{"length":227,"name":"xingxingYS","parent":"root","transform":{"x":-1.05,"y":2.1,"skX":90,"skY":90}},{"length":56,"name":"xingxingyx","parent":"root","transform":{"y":5.15,"skX":-1.0104,"skY":-1.0104}},{"length":72,"name":"xingxingLs","parent":"root","transform":{"x":-1.05,"y":4.15,"skX":-89.1668,"skY":-89.1668}},{"length":91,"name":"xingxingLX","parent":"root","transform":{"x":-1.05,"y":4.15,"skX":90,"skY":90}}],"slot":[{"name":"caidai","parent":"caidai"},{"name":"zhongwen","parent":"caidai"},{"name":"weiyuzixiugai","parent":"caidai"},{"name":"xingxingyx_00000","parent":"xingxingyx"},{"name":"xingxingYS_00000","parent":"xingxingYS"},{"name":"xingxingLX_00000","parent":"xingxingLX"},{"name":"xingxingLs_00000","parent":"xingxingLs"},{"name":"wuyu_00000","parent":"saoguang"},{"displayIndex":7,"name":"zhongwen_00000","parent":"saoguang"}],"skin":[{"slot":[{"name":"xingxingyx_00000","display":[{"name":"xingxingyx_00000","transform":{"x":29.54,"y":-30.13,"skX":1.01,"skY":1.01}},{"name":"xingxingyx_00001","transform":{"x":82.97,"y":-25.69,"skX":1.01,"skY":1.01}},{"name":"xingxingyx_00002","transform":{"x":135.76,"y":-13.76,"skX":1.01,"skY":1.01}},{"name":"xingxingyx_00003","transform":{"x":191.03,"y":0.22,"skX":1.01,"skY":1.01}},{"name":"xingxingyx_00004","transform":{"x":245.79,"y":14.19,"skX":1.01,"skY":1.01}},{"name":"xingxingyx_00005","transform":{"x":299,"y":31.13,"skX":1.01,"skY":1.01}}]},{"name":"xingxingYS_00000","display":[{"name":"xingxingYS_00000","transform":{"x":0.4,"y":-30.55,"skX":-90,"skY":-90}},{"name":"xingxingYS_00001","transform":{"x":-11.6,"y":-108.05,"skX":-90,"skY":-90}},{"name":"xingxingYS_00002","transform":{"x":-19.6,"y":-182.05,"skX":-90,"skY":-90}},{"name":"xingxingYS_00003","transform":{"x":-27.1,"y":-259.05,"skX":-90,"skY":-90}},{"name":"xingxingYS_00004","transform":{"x":-26.6,"y":-338.05,"skX":-90,"skY":-90}}]},{"name":"xingxingLX_00000","display":[{"name":"xingxingLX_00000","transform":{"x":26.35,"y":21.95,"skX":-90,"skY":-90}},{"name":"xingxingLX_00001","transform":{"x":30.85,"y":94.95,"skX":-90,"skY":-90}},{"name":"xingxingLX_00002","transform":{"x":37.85,"y":167.45,"skX":-90,"skY":-90}},{"name":"xingxingLX_00003","transform":{"x":45.85,"y":238.95,"skX":-90,"skY":-90}},{"name":"xingxingLX_00004","transform":{"x":56.85,"y":308.45,"skX":-90,"skY":-90}}]},{"name":"xingxingLs_00000","display":[{"name":"xingxingLs_00000","transform":{"x":23.29,"y":9.71,"skX":89.17,"skY":89.17}},{"name":"xingxingLs_00001","transform":{"x":32.46,"y":-13.42,"skX":89.17,"skY":89.17}},{"name":"xingxingLs_00002","transform":{"x":44.72,"y":-64.11,"skX":89.17,"skY":89.17}},{"name":"xingxingLs_00003","transform":{"x":57.33,"y":-125.3,"skX":89.17,"skY":89.17}},{"name":"xingxingLs_00004","transform":{"x":65.53,"y":-180.92,"skX":89.17,"skY":89.17}},{"name":"xingxingLs_00005","transform":{"x":62.64,"y":-207.38,"skX":89.17,"skY":89.17}}]},{"name":"wuyu_00000","display":[{"name":"wuyu_00000","transform":{"x":45.1,"y":-43.5,"skX":90,"skY":90}},{"name":"wuyu_00001","transform":{"x":44.1,"y":-51,"skX":90,"skY":90}},{"name":"wuyu_00002","transform":{"x":36.6,"y":-11,"skX":90,"skY":90}},{"name":"wuyu_00003","transform":{"x":40.6,"y":16,"skX":90,"skY":90}},{"name":"wuyu_00004","transform":{"x":42.6,"y":43,"skX":90,"skY":90}},{"name":"wuyu_00005","transform":{"x":26.1,"y":46.5,"skX":90,"skY":90}},{"name":"wuyu_00006","transform":{"x":34.1,"y":40.5,"skX":90,"skY":90}},{"name":"wuyu_00007","transform":{"x":37.6,"y":-2,"skX":90,"skY":90}}]},{"name":"caidai","display":[{"name":"caidai","transform":{"x":-1.05,"y":-1,"skX":-179.78,"skY":-179.78}}]},{"name":"zhongwen_00000","display":[{"name":"zhongwen_00000","transform":{"x":45.1,"y":-43.5,"skX":90,"skY":90}},{"name":"zhongwen_00001","transform":{"x":44.1,"y":-51,"skX":90,"skY":90}},{"name":"zhongwen_00002","transform":{"x":36.6,"y":-11,"skX":90,"skY":90}},{"name":"zhongwen_00003","transform":{"x":40.6,"y":16,"skX":90,"skY":90}},{"name":"zhongwen_00004","transform":{"x":42.6,"y":43,"skX":90,"skY":90}},{"name":"zhongwen_00005","transform":{"x":26.1,"y":46.5,"skX":90,"skY":90}},{"name":"zhongwen_00006","transform":{"x":34.1,"y":40.5,"skX":90,"skY":90}},{"name":"zhongwen_00007","transform":{"x":37.6,"y":-2,"skX":90,"skY":90}}]},{"name":"zhongwen","display":[{"name":"zhongwen","transform":{"x":6.86,"y":24.53,"skX":-179.78,"skY":-179.78}}]},{"name":"weiyuzixiugai","display":[{"name":"weiyuzixiugai","transform":{"y":5.45,"skX":-179.78,"skY":-179.78}}]}]}],"animation":[{"duration":24,"playTimes":0,"name":"huodezhongwen","bone":[{"name":"caidai","scaleFrame":[{"duration":2,"tweenEasing":0,"x":0.68},{"tweenEasing":0,"x":0.68},{"duration":2,"tweenEasing":0,"x":0.84},{"tweenEasing":0,"x":0.84},{"duration":18}]}],"slot":[{"name":"xingxingyx_00000","displayFrame":[{"duration":3},{"duration":3,"value":1},{"duration":3,"value":2},{"duration":3,"value":3},{"duration":3,"value":4},{"duration":9,"value":5}],"colorFrame":[{"duration":9,"tweenEasing":0,"value":{"aM":0}},{"duration":15}]},{"name":"xingxingYS_00000","displayFrame":[{"duration":3},{"duration":3,"value":1},{"duration":3,"value":2},{"duration":3,"value":3},{"duration":12,"value":4}],"colorFrame":[{"duration":6,"tweenEasing":0,"value":{"aM":0}},{"duration":6,"tweenEasing":0,"value":{"aM":50}},{"duration":12}]},{"name":"xingxingLX_00000","displayFrame":[{"duration":3},{"duration":3,"value":1},{"duration":3,"value":2},{"duration":3,"value":3},{"duration":12,"value":4}],"colorFrame":[{"duration":6,"tweenEasing":0,"value":{"aM":0}},{"duration":6,"tweenEasing":0,"value":{"aM":87}},{"duration":12}]},{"name":"xingxingLs_00000","displayFrame":[{"duration":3},{"duration":3,"value":1},{"duration":3,"value":2},{"duration":3,"value":3},{"duration":3,"value":4},{"duration":9,"value":5}],"colorFrame":[{"duration":6,"tweenEasing":0,"value":{"aM":10}},{"duration":9,"tweenEasing":0,"value":{"aM":83}},{"duration":9}]},{"name":"wuyu_00000","displayFrame":[{"duration":24,"value":-1}]},{"name":"zhongwen_00000","displayFrame":[{"duration":3},{"duration":3,"value":1},{"duration":3,"value":2},{"duration":3,"value":3},{"duration":3,"value":4},{"duration":3,"value":5},{"duration":3,"value":6},{"duration":3,"value":7},{"duration":0,"value":-1}]},{"name":"weiyuzixiugai","displayFrame":[{"duration":24,"value":-1}]}]},{"duration":24,"playTimes":0,"name":"huodeweiyu","bone":[{"name":"caidai","scaleFrame":[{"duration":2,"tweenEasing":0,"x":0.68},{"tweenEasing":0,"x":0.68},{"duration":2,"tweenEasing":0,"x":0.84},{"tweenEasing":0,"x":0.84},{"duration":18}]}],"slot":[{"name":"zhongwen","displayFrame":[{"duration":24,"value":-1}]},{"name":"xingxingyx_00000","displayFrame":[{"duration":3},{"duration":3,"value":1},{"duration":3,"value":2},{"duration":3,"value":3},{"duration":3,"value":4},{"duration":9,"value":5}],"colorFrame":[{"duration":9,"tweenEasing":0,"value":{"aM":0}},{"duration":15}]},{"name":"xingxingYS_00000","displayFrame":[{"duration":3},{"duration":3,"value":1},{"duration":3,"value":2},{"duration":3,"value":3},{"duration":12,"value":4}],"colorFrame":[{"duration":6,"tweenEasing":0,"value":{"aM":0}},{"duration":6,"tweenEasing":0,"value":{"aM":50}},{"duration":12}]},{"name":"xingxingLX_00000","displayFrame":[{"duration":3},{"duration":3,"value":1},{"duration":3,"value":2},{"duration":3,"value":3},{"duration":12,"value":4}],"colorFrame":[{"duration":6,"tweenEasing":0,"value":{"aM":0}},{"duration":6,"tweenEasing":0,"value":{"aM":87}},{"duration":12}]},{"name":"xingxingLs_00000","displayFrame":[{"duration":3},{"duration":3,"value":1},{"duration":3,"value":2},{"duration":3,"value":3},{"duration":3,"value":4},{"duration":9,"value":5}],"colorFrame":[{"duration":6,"tweenEasing":0,"value":{"aM":10}},{"duration":9,"tweenEasing":0,"value":{"aM":83}},{"duration":9}]},{"name":"wuyu_00000","displayFrame":[{"duration":3},{"duration":3,"value":1},{"duration":3,"value":2},{"duration":3,"value":3},{"duration":3,"value":4},{"duration":3,"value":5},{"duration":3,"value":6},{"duration":3,"value":7},{"duration":0,"value":-1}]},{"name":"zhongwen_00000","displayFrame":[{"duration":24,"value":-1}]}]}],"defaultActions":[{"gotoAndPlay":"huodezhongwen"}]}]}